simplevc/__init__.py
simplevc/simplevc.py
simplevc-0.0.4.dist-info/METADATA
simplevc-0.0.4.dist-info/WHEEL
simplevc-0.0.4.dist-info/top_level.txt
simplevc-0.0.4.dist-info/RECORD
