Metadata-Version: 2.1
Name: simplevc
Version: 0.0.4
Summary: A simple Python version control package
Home-page: https://github.com/aldenleung/simplevc/
Author: Alden Leung
Author-email: alden.leung@gmail.com
Classifier: Programming Language :: Python :: 3.9
Classifier: License :: OSI Approved :: GNU General Public License v3 (GPLv3)
